local_mutex.py
setup.py
local_mutex.egg-info/PKG-INFO
local_mutex.egg-info/SOURCES.txt
local_mutex.egg-info/dependency_links.txt
local_mutex.egg-info/top_level.txt